PyCSVSummarizer/CSVSummarizer.py
PyCSVSummarizer/__init__.py
PyCSVSummarizer-1.0.4.dist-info/License
PyCSVSummarizer-1.0.4.dist-info/METADATA
PyCSVSummarizer-1.0.4.dist-info/WHEEL
PyCSVSummarizer-1.0.4.dist-info/top_level.txt
PyCSVSummarizer-1.0.4.dist-info/RECORD
