Metadata-Version: 2.1
Name: PyCSVSummarizer
Version: 1.0.4
Summary: A lightweight tool to summarize CSV files using various features.
Author: Md. Ismiel Hossen Abir
Author-email: ismielabir1971@gmail.com
Classifier: Programming Language :: Python :: 3
Classifier: License :: OSI Approved :: MIT License
Classifier: Operating System :: OS Independent
Requires-Python: >=3.6
License-File: License
